speechlib/__init__.py
speechlib/convert_to_mono.py
speechlib/convert_to_wav.py
speechlib/core_analysis.py
speechlib/re_encode.py
speechlib/speaker_recognition.py
speechlib/speechlib.py
speechlib/transcribe.py
speechlib/wav_segmenter.py
speechlib/whisper_sinhala.py
speechlib/write_log_file.py
speechlib-1.1.12.dist-info/LICENSE
speechlib-1.1.12.dist-info/METADATA
speechlib-1.1.12.dist-info/WHEEL
speechlib-1.1.12.dist-info/top_level.txt
speechlib-1.1.12.dist-info/RECORD
