Metadata-Version: 2.1
Name: speechlib
Version: 1.1.12
Summary: speechlib is a library that can do speaker diarization, transcription and speaker recognition on an audio file to create transcripts with actual speaker names. This library also contain audio preprocessor functions.
Home-page: https://github.com/NavodPeiris/speechlib
Author: Navod Peiris
Author-email: navodpeiris1234@gmail.com
License: MIT
Classifier: License :: OSI Approved :: MIT License
Classifier: Programming Language :: Python :: 3.10
Classifier: Operating System :: OS Independent
Requires-Python: >=3.8
License-File: LICENSE
Requires-Dist: transformers
Requires-Dist: torch
Requires-Dist: torchaudio
Requires-Dist: pydub
Requires-Dist: pyannote.audio
Requires-Dist: speechbrain
Requires-Dist: accelerate
Requires-Dist: faster-whisper
Requires-Dist: openai-whisper
Requires-Dist: assemblyai
